odoo9_addon_account_cost_center-9.0.1.0.0.99.dev8-py3.8-nspkg.pth
odoo_addons/account_cost_center/README.rst
odoo_addons/account_cost_center/__init__.py
odoo_addons/account_cost_center/__openerp__.py
odoo_addons/account_cost_center/i18n/account_cost_center.pot
odoo_addons/account_cost_center/i18n/am.po
odoo_addons/account_cost_center/i18n/ar.po
odoo_addons/account_cost_center/i18n/bg.po
odoo_addons/account_cost_center/i18n/bs.po
odoo_addons/account_cost_center/i18n/ca.po
odoo_addons/account_cost_center/i18n/ca_ES.po
odoo_addons/account_cost_center/i18n/cs.po
odoo_addons/account_cost_center/i18n/da.po
odoo_addons/account_cost_center/i18n/de.po
odoo_addons/account_cost_center/i18n/el_GR.po
odoo_addons/account_cost_center/i18n/en_GB.po
odoo_addons/account_cost_center/i18n/es.po
odoo_addons/account_cost_center/i18n/es_AR.po
odoo_addons/account_cost_center/i18n/es_CL.po
odoo_addons/account_cost_center/i18n/es_CO.po
odoo_addons/account_cost_center/i18n/es_CR.po
odoo_addons/account_cost_center/i18n/es_DO.po
odoo_addons/account_cost_center/i18n/es_EC.po
odoo_addons/account_cost_center/i18n/es_ES.po
odoo_addons/account_cost_center/i18n/es_MX.po
odoo_addons/account_cost_center/i18n/es_PE.po
odoo_addons/account_cost_center/i18n/es_PY.po
odoo_addons/account_cost_center/i18n/es_VE.po
odoo_addons/account_cost_center/i18n/et.po
odoo_addons/account_cost_center/i18n/eu.po
odoo_addons/account_cost_center/i18n/fa.po
odoo_addons/account_cost_center/i18n/fi.po
odoo_addons/account_cost_center/i18n/fr.po
odoo_addons/account_cost_center/i18n/fr_CA.po
odoo_addons/account_cost_center/i18n/fr_CH.po
odoo_addons/account_cost_center/i18n/gl.po
odoo_addons/account_cost_center/i18n/gl_ES.po
odoo_addons/account_cost_center/i18n/gu.po
odoo_addons/account_cost_center/i18n/he.po
odoo_addons/account_cost_center/i18n/hr.po
odoo_addons/account_cost_center/i18n/hr_HR.po
odoo_addons/account_cost_center/i18n/hu.po
odoo_addons/account_cost_center/i18n/id.po
odoo_addons/account_cost_center/i18n/it.po
odoo9_addon_account_cost_center-9.0.1.0.0.99.dev8.dist-info/METADATA
odoo9_addon_account_cost_center-9.0.1.0.0.99.dev8.dist-info/WHEEL
odoo9_addon_account_cost_center-9.0.1.0.0.99.dev8.dist-info/namespace_packages.txt
odoo9_addon_account_cost_center-9.0.1.0.0.99.dev8.dist-info/top_level.txt
odoo9_addon_account_cost_center-9.0.1.0.0.99.dev8.dist-info/RECORD
