Metadata-Version: 2.1
Name: odoo9-addon-account-cost-center
Version: 9.0.1.0.0.99.dev8
Summary: Cost center information for invoice lines
Home-page: https://github.com/OCA/account-financial-tools/
Author: Onestein, Odoo Community Association (OCA)
Author-email: support@odoo-community.org
License: AGPL-3
Platform: UNKNOWN
Classifier: Programming Language :: Python
Classifier: Framework :: Odoo
Classifier: Framework :: Odoo :: 9.0
Classifier: License :: OSI Approved :: GNU Affero General Public License v3
Requires-Python: ~=2.7
Requires-Dist: odoo9-addon-base-view-inheritance-extension
Requires-Dist: odoo (<9.1a,>=9.0a)
